{"items": [{"name": "compile-time", "is_moderator_only": false, "has_synonyms": false, "is_required": false, "count": 470}, {"name": "ip-camera", "is_moderator_only": false, "has_synonyms": false, "is_required": false, "count": 470}, {"name": "least-squares", "is_moderator_only": false, "has_synonyms": false, "is_required": false, "count": 470}, {"name": "presentmodalviewcontrolle", "is_moderator_only": false, "has_synonyms": false, "is_required": false, "count": 470}, {"name": "software-distribution", "is_moderator_only": false, "has_synonyms": false, "is_required": false, "count": 469}, {"name": "gnu-screen", "is_moderator_only": false, "has_synonyms": false, "is_required": false, "count": 469}, {"name": "minimize", "is_moderator_only": false, "has_synonyms": false, "is_required": false, "count": 469}, {"name": "predict", "is_moderator_only": false, "has_synonyms": false, "is_required": false, "count": 469}, {"name": "qtgui", "is_moderator_only": false, "has_synonyms": false, "is_required": false, "count": 469}, {"name": "html5-appcache", "is_moderator_only": false, "has_synonyms": false, "is_required": false, "count": 469}, {"name": "active-model-serializers", "is_moderator_only": false, "has_synonyms": false, "is_required": false, "count": 469}, {"name": "ruby-2.0", "is_moderator_only": false, "has_synonyms": false, "is_required": false, "count": 469}, {"name": "sharepoint-online", "is_moderator_only": false, "has_synonyms": false, "is_required": false, "count": 469}, {"name": "firebase-storage", "is_moderator_only": false, "has_synonyms": false, "is_required": false, "count": 469}, {"name": "form-data", "is_moderator_only": false, "has_synonyms": false, "is_required": false, "count": 468}, {"name": "itemtemplate", "is_moderator_only": false, "has_synonyms": false, "is_required": false, "count": 468}, {"name": "anonymous-class", "is_moderator_only": false, "has_synonyms": false, "is_required": false, "count": 468}, {"name": "raw-input", "is_moderator_only": false, "has_synonyms": false, "is_required": false, "count": 468}, {"name": "optaplanner", "is_moderator_only": false, "has_synonyms": false, "is_required": false, "count": 468}, {"name": "stax", "is_moderator_only": false, "has_synonyms": false, "is_required": false, "count": 467}, {"name": "system.diagnostics", "is_moderator_only": false, "has_synonyms": false, "is_required": false, "count": 467}, {"name": "zend-studio", "is_moderator_only": false, "has_synonyms": false, "is_required": false, "count": 467}, {"name": "stringtokenizer", "is_moderator_only": false, "has_synonyms": false, "is_required": false, "count": 467}, {"name": "facebook-ads-api", "is_moderator_only": false, "has_synonyms": false, "is_required": false, "count": 467}, {"name": "ef-database-first", "is_moderator_only": false, "has_synonyms": false, "is_required": false, "count": 467}, {"name": "django-migrations", "is_moderator_only": false, "has_synonyms": false, "is_required": false, "count": 467}, {"name": "administrator", "is_moderator_only": false, "has_synonyms": false, "is_required": false, "count": 466}, {"name": "iso-8859-1", "is_moderator_only": false, "has_synonyms": true, "is_required": false, "count": 466}, {"name": "recv", "is_moderator_only": false, "has_synonyms": false, "is_required": false, "count": 466}, {"name": "sbcl", "is_moderator_only": false, "has_synonyms": false, "is_required": false, "count": 465}, {"name": "gsoap", "is_moderator_only": false, "has_synonyms": false, "is_required": false, "count": 465}, {"name": "msbuild-task", "is_moderator_only": false, "has_synonyms": false, "is_required": false, "count": 465}, {"name": "greedy", "is_moderator_only": false, "has_synonyms": false, "is_required": false, "count": 465}, {"name": "string-literals", "is_moderator_only": false, "has_synonyms": true, "is_required": false, "count": 465}, {"name": "bitset", "is_moderator_only": false, "has_synonyms": false, "is_required": false, "count": 465}, {"name": "httpsession", "is_moderator_only": false, "has_synonyms": false, "is_required": false, "count": 465}, {"name": "uiapplicationdelegate", "is_moderator_only": false, "has_synonyms": false, "is_required": false, "count": 465}, {"name": "bing-api", "is_moderator_only": false, "has_synonyms": false, "is_required": false, "count": 465}, {"name": "google-tv", "is_moderator_only": false, "has_synonyms": false, "is_required": false, "count": 465}, {"name": "mongolab", "is_moderator_only": false, "has_synonyms": false, "is_required": false, "count": 465}, {"name": "ggvis", "is_moderator_only": false, "has_synonyms": false, "is_required": false, "count": 465}, {"name": "dynamics-crm-2015", "is_moderator_only": false, "has_synonyms": false, "is_required": false, "count": 465}, {"name": "oci", "is_moderator_only": false, "has_synonyms": false, "is_required": false, "count": 464}, {"name": "quickfix", "is_moderator_only": false, "has_synonyms": false, "is_required": false, "count": 464}, {"name": "jqtouch", "is_moderator_only": false, "has_synonyms": false, "is_required": false, "count": 464}, {"name": "sapply", "is_moderator_only": false, "has_synonyms": false, "is_required": false, "count": 464}, {"name": "sharekit", "is_moderator_only": false, "has_synonyms": false, "is_required": false, "count": 464}, {"name": "pusher", "is_moderator_only": false, "has_synonyms": false, "is_required": false, "count": 464}, {"name": "back-stack", "is_moderator_only": false, "has_synonyms": false, "is_required": false, "count": 464}, {"name": "clipping", "is_moderator_only": false, "has_synonyms": false, "is_required": false, "count": 463}, {"name": "self-signed", "is_moderator_only": false, "has_synonyms": false, "is_required": false, "count": 463}, {"name": "freetds", "is_moderator_only": false, "has_synonyms": false, "is_required": false, "count": 463}, {"name": "faceted-search", "is_moderator_only": false, "has_synonyms": false, "is_required": false, "count": 463}, {"name": "pg", "is_moderator_only": false, "has_synonyms": false, "is_required": false, "count": 463}, {"name": "django-staticfiles", "is_moderator_only": false, "has_synonyms": false, "is_required": false, "count": 463}, {"name": "keyup", "is_moderator_only": false, "has_synonyms": false, "is_required": false, "count": 463}, {"name": "vnc", "is_moderator_only": false, "has_synonyms": false, "is_required": false, "count": 462}, {"name": "catalyst", "is_moderator_only": false, "has_synonyms": false, "is_required": false, "count": 462}, {"name": "base-class", "is_moderator_only": false, "has_synonyms": true, "is_required": false, "count": 462}, {"name": "self-hosting", "is_moderator_only": false, "has_synonyms": false, "is_required": false, "count": 462}, {"name": "malware", "is_moderator_only": false, "has_synonyms": false, "is_required": false, "count": 462}, {"name": "nscoding", "is_moderator_only": false, "has_synonyms": false, "is_required": false, "count": 462}, {"name": "nssortdescriptor", "is_moderator_only": false, "has_synonyms": false, "is_required": false, "count": 462}, {"name": "rcurl", "is_moderator_only": false, "has_synonyms": false, "is_required": false, "count": 462}, {"name": "neo4jclient", "is_moderator_only": false, "has_synonyms": false, "is_required": false, "count": 462}, {"name": "openerp-8", "is_moderator_only": false, "has_synonyms": false, "is_required": false, "count": 462}, {"name": "feeds", "is_moderator_only": false, "has_synonyms": false, "is_required": false, "count": 461}, {"name": "upsert", "is_moderator_only": false, "has_synonyms": false, "is_required": false, "count": 461}, {"name": "ado.net-entity-data-model", "is_moderator_only": false, "has_synonyms": false, "is_required": false, "count": 461}, {"name": "database-restore", "is_moderator_only": false, "has_synonyms": false, "is_required": false, "count": 461}, {"name": "removechild", "is_moderator_only": false, "has_synonyms": false, "is_required": false, "count": 461}, {"name": "bit-fields", "is_moderator_only": false, "has_synonyms": true, "is_required": false, "count": 461}, {"name": "android-checkbox", "is_moderator_only": false, "has_synonyms": false, "is_required": false, "count": 461}, {"name": "java-3d", "is_moderator_only": false, "has_synonyms": false, "is_required": false, "count": 460}, {"name": "manager", "is_moderator_only": false, "has_synonyms": true, "is_required": false, "count": 460}, {"name": "drawimage", "is_moderator_only": false, "has_synonyms": false, "is_required": false, "count": 460}, {"name": "alphabetical", "is_moderator_only": false, "has_synonyms": false, "is_required": false, "count": 460}, {"name": "master-slave", "is_moderator_only": false, "has_synonyms": false, "is_required": false, "count": 460}, {"name": "kdb", "is_moderator_only": false, "has_synonyms": false, "is_required": false, "count": 460}, {"name": "cardlayout", "is_moderator_only": false, "has_synonyms": false, "is_required": false, "count": 460}, {"name": "peewee", "is_moderator_only": false, "has_synonyms": false, "is_required": false, "count": 460}, {"name": "forwarding", "is_moderator_only": false, "has_synonyms": false, "is_required": false, "count": 459}, {"name": "skip", "is_moderator_only": false, "has_synonyms": false, "is_required": false, "count": 459}, {"name": "conditional-compilation", "is_moderator_only": false, "has_synonyms": true, "is_required": false, "count": 459}, {"name": "stage", "is_moderator_only": false, "has_synonyms": false, "is_required": false, "count": 459}, {"name": "observers", "is_moderator_only": false, "has_synonyms": false, "is_required": false, "count": 459}, {"name": "jeditorpane", "is_moderator_only": false, "has_synonyms": false, "is_required": false, "count": 459}, {"name": "dom-manipulation", "is_moderator_only": false, "has_synonyms": false, "is_required": false, "count": 459}, {"name": "ns2", "is_moderator_only": false, "has_synonyms": false, "is_required": false, "count": 459}, {"name": "mouseenter", "is_moderator_only": false, "has_synonyms": false, "is_required": false, "count": 459}, {"name": "interrupt-handling", "is_moderator_only": false, "has_synonyms": false, "is_required": false, "count": 459}, {"name": "concrete5", "is_moderator_only": false, "has_synonyms": false, "is_required": false, "count": 459}, {"name": "acts-as-taggable-on", "is_moderator_only": false, "has_synonyms": false, "is_required": false, "count": 459}, {"name": "linuxmint", "is_moderator_only": false, "has_synonyms": false, "is_required": false, "count": 459}, {"name": "landscape-portrait", "is_moderator_only": false, "has_synonyms": false, "is_required": false, "count": 459}, {"name": "hdinsight", "is_moderator_only": false, "has_synonyms": false, "is_required": false, "count": 459}, {"name": "application-server", "is_moderator_only": false, "has_synonyms": false, "is_required": false, "count": 458}, {"name": "trait", "is_moderator_only": false, "has_synonyms": false, "is_required": false, "count": 458}, {"name": "sage", "is_moderator_only": false, "has_synonyms": false, "is_required": false, "count": 458}, {"name": "tree-traversal", "is_moderator_only": false, "has_synonyms": false, "is_required": false, "count": 458}], "quota_max": 10000, "has_more": true, "quota_remaining": 9931}